{
  "parent": "minecraft:recipes/root",
  "criteria": {
    "has_mithirl_ore": {
      "conditions": {
        "items": [
          {
            "items": "fantasymod:mithirl_ore"
          }
        ]
      },
      "trigger": "minecraft:inventory_changed"
    },
    "has_the_recipe": {
      "conditions": {
        "recipe": "minecraft:raw_mithirl_from_blasting_mithirl_ore"
      },
      "trigger": "minecraft:recipe_unlocked"
    }
  },
  "requirements": [
    [
      "has_the_recipe",
      "has_mithirl_ore"
    ]
  ],
  "rewards": {
    "recipes": [
      "minecraft:raw_mithirl_from_blasting_mithirl_ore"
    ]
  }
}